{"Mesh_description": "squareWithTriangles", "Mesh_dim": 2, "Errors": [0.7503307283176518, 0.2539544973957279, 0.10870368061041591, 0.055777341080608625, 0.028297242335636467, 0.014264092354052018], "Test_color": "Orange (ILU)", "PDE_is_stationary": true, "Mesh_cell_type": "Triangles", "Mesh_type": "Regular_RightTriangles", "Mesh_names": [5, 20, 50, 100, 200, 400], "Bound_cond": "Neumann", "Mesh_sizes": [7.071067811865475, 28.284271247461906, 70.71067811865474, 141.4213562373095, 282.8427124746191, 565.6854249492382], "Num_method": "FE", "PDE_search_for_stationary_solution": false, "Initial_data": "None", "Part_of_mesh_convergence_analysis": true, "Scheme_order": 0.9103, "Mesh_is_unstructured": true, "Space_dim": 2, "Numerical_method_time_discretization": "None", "PDE_model": "Poisson", "Comput_time": 26.158}