{"Mesh_description": "squareWithSquares", "Mesh_dim": 2, "Errors": [0.03355839110269998, 0.002058706764535256, 0.0003290517629437446, 8.225076220744793e-05, 2.0561929520497192e-05, 5.1404348144457395e-06], "Test_color": "Green", "PDE_is_stationary": true, "Mesh_cell_type": "Squares", "Mesh_type": "RegularSquares", "Mesh_names": [5, 20, 50, 100, 200, 400], "Bound_cond": "Dirichlet", "Mesh_sizes": [5.000000000000001, 20.000000000000004, 49.99999999999999, 100.0, 200.00000000000003, 400.0000000000001], "Num_method": "FV", "PDE_search_for_stationary_solution": false, "Initial_data": "None", "Part_of_mesh_convergence_analysis": true, "Scheme_order": 2.0039, "Mesh_is_unstructured": true, "Space_dim": 2, "Numerical_method_time_discretization": "None", "PDE_model": "Poisson", "Comput_time": 10.755}